{
  "db_name": "PostgreSQL",
  "query": "\n        SELECT p.id, p.nombre,\n               COALESCE(p.markup_pct_override, c.markup_pct) AS \"markup_pct!\",\n               COALESCE(p.iva_pct_override, c.iva_pct) AS \"iva_pct!\",\n               p.controla_vencimiento\n        FROM catalogo.productos p\n        JOIN catalogo.categorias c ON c.id = p.categoria_id\n        WHERE p.id = $1 AND p.activo\n        ",
  "describe": {
    "columns": [
      {
        "ordinal": 0,
        "name": "id",
        "type_info": "Uuid"
      },
      {
        "ordinal": 1,
        "name": "nombre",
        "type_info": "Text"
      },
      {
        "ordinal": 2,
        "name": "markup_pct!",
        "type_info": "Numeric"
      },
      {
        "ordinal": 3,
        "name": "iva_pct!",
        "type_info": "Numeric"
      },
      {
        "ordinal": 4,
        "name": "controla_vencimiento",
        "type_info": "Bool"
      }
    ],
    "parameters": {
      "Left": [
        "Uuid"
      ]
    },
    "nullable": [
      false,
      false,
      null,
      null,
      false
    ]
  },
  "hash": "5980553dfeb94a22ec545b94a2389a6db089d4def73a716092699d16a9640c7b"
}
