{
  "db_name": "PostgreSQL",
  "query": "\n        SELECT COALESCE(SUM(total_centavos), 0)::bigint AS \"facturado!\",\n               COUNT(*) AS \"tickets!\",\n               COALESCE(SUM(descuento_centavos), 0)::bigint AS \"descuentos!\"\n        FROM ventas.ventas\n        WHERE estado = 'confirmada'\n          AND (vendida_en AT TIME ZONE $3)::date BETWEEN $1 AND $2\n        ",
  "describe": {
    "columns": [
      {
        "ordinal": 0,
        "name": "facturado!",
        "type_info": "Int8"
      },
      {
        "ordinal": 1,
        "name": "tickets!",
        "type_info": "Int8"
      },
      {
        "ordinal": 2,
        "name": "descuentos!",
        "type_info": "Int8"
      }
    ],
    "parameters": {
      "Left": [
        "Date",
        "Date",
        "Text"
      ]
    },
    "nullable": [
      null,
      null,
      null
    ]
  },
  "hash": "86d34f7c04ab6e833282ae7bf7433dae2615f84b6043fea84542ee9269640c17"
}
